rest_framework_casdoor/__init__.py
rest_framework_casdoor/admin.py
rest_framework_casdoor/apps.py
rest_framework_casdoor/authentication.py
rest_framework_casdoor/backends.py
rest_framework_casdoor/models.py
rest_framework_casdoor/settings.py
rest_framework_casdoor/tests.py
rest_framework_casdoor/urls.py
rest_framework_casdoor/views.py
rest_framework_casdoor/migrations/__init__.py
djangorestframework_casdoor-1.0.dist-info/LICENSE
djangorestframework_casdoor-1.0.dist-info/METADATA
djangorestframework_casdoor-1.0.dist-info/WHEEL
djangorestframework_casdoor-1.0.dist-info/top_level.txt
djangorestframework_casdoor-1.0.dist-info/RECORD
