Metadata-Version: 2.1
Name: djangorestframework-casdoor
Version: 1.0
Summary: djangorestframework-casdoor is a Django REST framework authentication plugin for Casdoor.
Home-page: https://github.com/Anion3r/djangorestframework-casdoor.git
Author: Anioner
Author-email: Anioner <anioner@qq.com>
License: Apache License 2.0
Project-URL: Homepage, https://github.com/Anion3r/djangorestframework-casdoor
Project-URL: Bug Tracker, https://github.com/Anion3r/djangorestframework-casdoor/issues
Classifier: Programming Language :: Python :: 3
Classifier: License :: OSI Approved :: Apache Software License
Classifier: Operating System :: OS Independent
Requires-Python: >=3.6
License-File: LICENSE
Requires-Dist: Django
Requires-Dist: djangorestframework
Requires-Dist: casdoor
